ivy_sdk/__init__.py
ivy_sdk/sdk.py
ivy_sdk/sdkconfiguration.py
ivy_sdk/models/__init__.py
ivy_sdk/models/completeop.py
ivy_sdk/models/create_test_datasetop.py
ivy_sdk/models/create_testcaseop.py
ivy_sdk/models/evaluationdataset.py
ivy_sdk/models/health_check_unsecuredop.py
ivy_sdk/models/httpvalidationerror.py
ivy_sdk/models/promptcompletionrequest.py
ivy_sdk/models/rootop.py
ivy_sdk/models/run_testop.py
ivy_sdk/models/sdkerror.py
ivy_sdk/models/testcase.py
ivy_sdk/models/testcasecreate.py
ivy_sdk/models/testcasedataset.py
ivy_sdk/models/testdatasetcreate.py
ivy_sdk/models/validationerror.py
ivy_sdk/utils/__init__.py
ivy_sdk/utils/retries.py
ivy_sdk/utils/utils.py
IvyCheckPythonSDK-0.6.0.dist-info/LICENSE.md
IvyCheckPythonSDK-0.6.0.dist-info/METADATA
IvyCheckPythonSDK-0.6.0.dist-info/WHEEL
IvyCheckPythonSDK-0.6.0.dist-info/top_level.txt
IvyCheckPythonSDK-0.6.0.dist-info/RECORD
